pump_fun_self-1.0.2.dist-info/licenses/LICENCE
pump_self_melon/__init__.py
pump_self_melon/ban_manager.py
pump_self_melon/client.py
pump_self_melon/main.py
pump_self_melon/models.py
pump_self_melon/core/__init__.py
pump_self_melon/core/utils.py
pump_self_melon/core/ws.py
pump_self_melon/utils/__init__.py
pump_self_melon/utils/req.py
pump_fun_self-1.0.2.dist-info/METADATA
pump_fun_self-1.0.2.dist-info/WHEEL
pump_fun_self-1.0.2.dist-info/top_level.txt
pump_fun_self-1.0.2.dist-info/RECORD
