Metadata-Version: 2.4
Name: pump.fun-self
Version: 1.0.2
Summary: A discord.py-self-like library for pump.fun selfbot development
Author-email: melon <stevebsons@gmail.com>
License: MIT
Project-URL: Homepage, https://github.com/melon/pump-self
Project-URL: Repository, https://github.com/melon/pump-self
Project-URL: Issues, https://github.com/melon/pump-self/issues
Keywords: pump.fun,selfbot,discord.py,websocket,chat,bot
Classifier: Programming Language :: Python :: 3
Classifier: Programming Language :: Python :: 3.9
Classifier: Programming Language :: Python :: 3.10
Classifier: Programming Language :: Python :: 3.11
Classifier: Programming Language :: Python :: 3.12
Classifier: Operating System :: OS Independent
Classifier: Development Status :: 5 - Production/Stable
Classifier: Intended Audience :: Developers
Classifier: Topic :: Internet :: WWW/HTTP
Classifier: Topic :: Software Development :: Libraries :: Python Modules
Classifier: Topic :: Communications :: Chat
Requires-Python: >=3.9
License-File: LICENCE
Requires-Dist: websockets>=11.0.0
Requires-Dist: aiohttp>=3.8.0
Provides-Extra: dev
Requires-Dist: pytest>=7.0.0; extra == "dev"
Requires-Dist: pytest-asyncio>=0.21.0; extra == "dev"
Requires-Dist: pytest-cov>=4.0.0; extra == "dev"
Dynamic: license-file
